Metadata-Version: 1.0
Name: js.angular-scroll
Version: 0.6.2
Summary: Fanstatic packaging of angular-scroll
Home-page: UNKNOWN
Author: Fanstatic Developers
Author-email: fanstatic@googlegroups.com
License: BSD
Platform: UNKNOWN
